flowx/__init__.py
flowx/agents/__init__.py
flowx/agents/agent.py
flowx/callbacks/__init__.py
flowx/callbacks/callback_handler.py
flowx/callbacks/callback_manager.py
flowx/callbacks/chat_history.py
flowx/callbacks/console_callback.py
flowx/callbacks/listeners_callback.py
flowx/callbacks/run.py
flowx/callbacks/run_cache.py
flowx/callbacks/run_stack.py
flowx/callbacks/trace.py
flowx/cmdline.py
flowx/config/__init__.py
flowx/config/settings.yml
flowx/context.py
flowx/exceptions.py
flowx/flow/__init__.py
flowx/flow/addable_dict.py
flowx/flow/config.py
flowx/flow/flow.py
flowx/flow/utils.py
flowx/llm/__init__.py
flowx/llm/llm.py
flowx/llm/llm_with_history.py
flowx/llm/openai/__init__.py
flowx/llm/openai/openai_llm.py
flowx/llm/openai/utils.py
flowx/log.py
flowx/logging.py
flowx/messages/__init__.py
flowx/messages/chat_message.py
flowx/messages/utils.py
flowx/prompts/__init__.py
flowx/prompts/message_list_template.py
flowx/prompts/message_template.py
flowx/tool.py
flowx/utils/__init__.py
flowx/utils/iter.py
flowx/utils/utils.py
flowx-0.1.0.dist-info/LICENSE
flowx-0.1.0.dist-info/METADATA
flowx-0.1.0.dist-info/WHEEL
flowx-0.1.0.dist-info/entry_points.txt
flowx-0.1.0.dist-info/RECORD
