Metadata-Version: 2.1
Name: flowx
Version: 0.1.0
Summary: Elegant and lightweight, yet functionally comprehensive, the Flow framework is the best choice for large models.
License: MIT
Author: yihe yang
Author-email: yangchichi@126.com
Requires-Python: >=3.9,<3.13
Classifier: License :: OSI Approved :: MIT License
Classifier: Operating System :: OS Independent
Classifier: Programming Language :: Python :: 3
Classifier: Programming Language :: Python :: 3.9
Classifier: Programming Language :: Python :: 3.10
Classifier: Programming Language :: Python :: 3.11
Classifier: Programming Language :: Python :: 3.12
Requires-Dist: chromadb (>=0.5.3,<0.6.0)
Requires-Dist: click (>=8.1.3,<9.0.0)
Requires-Dist: docx2txt (>=0.8,<0.9)
Requires-Dist: dynaconf (>=3.1.12,<4.0.0)
Requires-Dist: nltk (>=3.8.1,<4.0.0)
Requires-Dist: numpy (>=1.21,<2.0)
Requires-Dist: openai (>=1.35.9,<2.0.0)
Requires-Dist: protobuf (>=5.27.2,<6.0.0)
Requires-Dist: pydantic (>=2.7.0)
Requires-Dist: pypdf (>=4.2.0,<5.0.0)
Requires-Dist: sentencepiece (>=0.2.0,<0.3.0)
Requires-Dist: tenacity (>=8.4.2,<9.0.0)
Requires-Dist: tiktoken (>=0.7.0,<0.8.0)
Requires-Dist: transformers (>=4.42.3,<5.0.0)
Requires-Dist: unstructured (>=0.14.9,<0.15.0)
